eduvpn/__init__.py
eduvpn/__main__.py
eduvpn/app.py
eduvpn/cli.py
eduvpn/config.py
eduvpn/connection.py
eduvpn/discovery.py
eduvpn/i18n.py
eduvpn/keyring.py
eduvpn/nm.py
eduvpn/notify.py
eduvpn/proxy.py
eduvpn/server.py
eduvpn/settings.py
eduvpn/storage.py
eduvpn/utils.py
eduvpn/variants.py
eduvpn/data/share/applications/org.eduvpn.client.desktop
eduvpn/data/share/applications/org.letsconnect-vpn.client.desktop
eduvpn/data/share/eduvpn/country_codes.json
eduvpn/data/share/eduvpn/eduvpn.png
eduvpn/data/share/eduvpn/builder/mainwindow.ui
eduvpn/data/share/eduvpn/images/app-icon-circle.svg
eduvpn/data/share/eduvpn/images/app-icon-circle@2x.png
eduvpn/data/share/eduvpn/images/app-icon-circle@3x.png
eduvpn/data/share/eduvpn/images/back.png
eduvpn/data/share/eduvpn/images/back@2x.png
eduvpn/data/share/eduvpn/images/back@3x.png
eduvpn/data/share/eduvpn/images/chevron-down.png
eduvpn/data/share/eduvpn/images/chevron-down@2x.png
eduvpn/data/share/eduvpn/images/chevron-down@3x.png
eduvpn/data/share/eduvpn/images/chevron-right-white.png
eduvpn/data/share/eduvpn/images/chevron-right-white@2x.png
eduvpn/data/share/eduvpn/images/chevron-right-white@3x.png
eduvpn/data/share/eduvpn/images/chevron-right.png
eduvpn/data/share/eduvpn/images/chevron-right@2x.png
eduvpn/data/share/eduvpn/images/chevron-right@3x.png
eduvpn/data/share/eduvpn/images/cross.png
eduvpn/data/share/eduvpn/images/cross@2x.png
eduvpn/data/share/eduvpn/images/cross@3x.png
eduvpn/data/share/eduvpn/images/desktop-connected.png
eduvpn/data/share/eduvpn/images/desktop-connected@2x.png
eduvpn/data/share/eduvpn/images/desktop-connected@3x.png
eduvpn/data/share/eduvpn/images/desktop-connecting.png
eduvpn/data/share/eduvpn/images/desktop-connecting@2x.png
eduvpn/data/share/eduvpn/images/desktop-connecting@3x.png
eduvpn/data/share/eduvpn/images/desktop-default.png
eduvpn/data/share/eduvpn/images/desktop-default@2x.png
eduvpn/data/share/eduvpn/images/desktop-default@3x.png
eduvpn_client-4.6.0.dist-info/licenses/LICENSE
eduvpn_client-4.6.0.dist-info/licenses/LICENSE.spdx
eduvpn_client-4.6.0.dist-info/METADATA
eduvpn_client-4.6.0.dist-info/WHEEL
eduvpn_client-4.6.0.dist-info/entry_points.txt
eduvpn_client-4.6.0.dist-info/top_level.txt
eduvpn_client-4.6.0.dist-info/RECORD
